mohtml/__init__.py
mohtml/anything.py
mohtml/parser.py
mohtml/components/__init__.py
mohtml/components/_chord.py
mohtml/components/_highlight.py
mohtml/components/_terminal.py
mohtml-0.1.11.dist-info/licenses/LICENSE
mohtml-0.1.11.dist-info/METADATA
mohtml-0.1.11.dist-info/WHEEL
mohtml-0.1.11.dist-info/top_level.txt
mohtml-0.1.11.dist-info/RECORD
