Metadata-Version: 2.4
Name: mohtml
Version: 0.1.11
Summary: DSL for Python to HTML aimed at Marimo
Author: Vincent D. Warmerdam
License: MIT License
Project-URL: repository, https://github.com/koaning/mohtml
Project-URL: issue-tracker, https://github.com/koaning/mohtml/issues
Project-URL: documentation, https://koaning.github.io/mohtml/
Classifier: Programming Language :: Python :: 3
Classifier: Programming Language :: Python :: 3.10
Classifier: Programming Language :: Python :: 3.11
Classifier: Programming Language :: Python :: 3.12
Classifier: License :: OSI Approved :: MIT License
Classifier: Topic :: Scientific/Engineering
Classifier: Topic :: Scientific/Engineering :: Artificial Intelligence
Classifier: Topic :: Software Development :: Libraries :: Python Modules
License-File: LICENSE
Requires-Dist: beautifulsoup4
Requires-Dist: marimo
Dynamic: license-file
